dvc_streamlit/__init__.py
dvc_streamlit/experiments.py
dvc_streamlit/metrics.py
dvc_streamlit/params.py
dvc_streamlit/plots.py
dvc_streamlit/repo.py
dvc_streamlit/rev_selector.py
dvc_streamlit/version.py
dvc_streamlit-0.0.2.dist-info/LICENSE
dvc_streamlit-0.0.2.dist-info/METADATA
dvc_streamlit-0.0.2.dist-info/WHEEL
dvc_streamlit-0.0.2.dist-info/top_level.txt
dvc_streamlit-0.0.2.dist-info/RECORD
