Metadata-Version: 2.1
Name: dvc-streamlit
Version: 0.0.2
Summary: Streamlit components for DVC.
Home-page: https://github.com/iterative/dvc_streamlit
Download-URL: https://github.com/iterative/dvc_streamlit
Author: David de la Iglesia Castro
Author-email: diglesia@iterative.ai
License: UNKNOWN
Platform: UNKNOWN
Requires-Python: >=3.7
License-File: LICENSE
Requires-Dist: dvc (>=2.7.4)
Requires-Dist: hiplot (>=0.1.29)
Requires-Dist: plotly (>=5.3.1)
Requires-Dist: streamlit (>=0.89.0)
Provides-Extra: tests
Requires-Dist: pytest (>=6.0.1) ; extra == 'tests'
Requires-Dist: pytest-mock (>=3.6.1) ; extra == 'tests'
Requires-Dist: pre-commit ; extra == 'tests'
